bitpulse/__init__.py
bitpulse/api/__init__.py
bitpulse/api/client.py
bitpulse/core/__init__.py
bitpulse/core/auto_tracer.py
bitpulse/core/core.py
bitpulse/core/exceptions.py
bitpulse/core/llm_tracer.py
bitpulse/core/settings.py
bitpulse/instrumentation/__init__.py
bitpulse/instrumentation/base.py
bitpulse/schemas/__init__.py
bitpulse/schemas/base.py
bitpulse/schemas/schema.py
bitpulse/schemas/types.py
bitpulse/storage/__init__.py
bitpulse/storage/base.py
bitpulse/storage/memory.py
bitpulse/utils/__init__.py
bitpulse/utils/config.py
bitpulse/utils/constants.py
bitpulse/utils/converter.py
bitpulse/utils/ingestion.py
bitpulse/utils/logging_utils.py
bitpulse/utils/metrics.py
bitpulse-0.1.0.dist-info/licenses/LICENSE.md
bitpulse-0.1.0.dist-info/METADATA
bitpulse-0.1.0.dist-info/WHEEL
bitpulse-0.1.0.dist-info/top_level.txt
bitpulse-0.1.0.dist-info/RECORD
