Metadata-Version: 2.4
Name: bitpulse
Version: 0.1.0
Summary: Automatically capture and send LLM trace data from GraphBit applications to your observability API endpoint
Author-email: GraphBit Team <contact@infinitibit.ai>
Maintainer-email: GraphBit Team <contact@infinitibit.ai>
License: # GRAPHBIT FRAMEWORK LICENSE
Project-URL: Homepage, https://github.com/InfinitiBit/bitpulse
Project-URL: Documentation, https://docs.graphbit.ai
Project-URL: Repository, https://github.com/InfinitiBit/bitpulse
Project-URL: Bug Tracker, https://github.com/InfinitiBit/bitpulse/issues
Keywords: observability,tracing,llm,monitoring,graphbit,api,http
Classifier: Development Status :: 4 - Beta
Classifier: Intended Audience :: Developers
Classifier: Operating System :: OS Independent
Classifier: Programming Language :: Python :: 3
Classifier: Programming Language :: Python :: 3.10
Classifier: Programming Language :: Python :: 3.11
Classifier: Programming Language :: Python :: 3.12
Classifier: Programming Language :: Python :: 3.13
Classifier: Programming Language :: Python :: 3 :: Only
Classifier: Typing :: Typed
Classifier: Topic :: Software Development :: Libraries :: Python Modules
Classifier: Topic :: System :: Monitoring
Classifier: Topic :: Scientific/Engineering :: Artificial Intelligence
Requires-Python: <3.14,>=3.10
License-File: LICENSE.md
Requires-Dist: pydantic>=2.0.0
Requires-Dist: pydantic-settings>=2.0.0
Requires-Dist: aiofiles>=23.0.0
Requires-Dist: httpx>=0.24.0
Requires-Dist: aiohttp>=3.8.0
Requires-Dist: graphbit>=0.5.0
Requires-Dist: pandas>=1.5.0
Requires-Dist: structlog>=23.0.0
Requires-Dist: python-dotenv>=1.0.0
Requires-Dist: loguru==0.7.3
Provides-Extra: dev
Requires-Dist: pytest>=7.0.0; extra == "dev"
Requires-Dist: pytest-asyncio>=0.21.0; extra == "dev"
Requires-Dist: pytest-cov>=4.0.0; extra == "dev"
Requires-Dist: pytest-mock>=3.11.0; extra == "dev"
Requires-Dist: black>=23.12.0; extra == "dev"
Requires-Dist: isort>=5.13.0; extra == "dev"
Requires-Dist: flake8>=6.0.0; extra == "dev"
Requires-Dist: pre-commit>=3.0.0; extra == "dev"
Requires-Dist: bandit>=1.7.0; extra == "dev"
Provides-Extra: export
Requires-Dist: pyarrow>=13.0.0; extra == "export"
Requires-Dist: openpyxl>=3.1.0; extra == "export"
Dynamic: license-file
